LICENSE
MANIFEST.in
README.rst
setup.py
gcm_client.egg-info/PKG-INFO
gcm_client.egg-info/SOURCES.txt
gcm_client.egg-info/dependency_links.txt
gcm_client.egg-info/requires.txt
gcm_client.egg-info/top_level.txt
gcmclient/__init__.py
gcmclient/gcm.py
gcmclient/test.py